br_regras_fiscais/__init__.py
br_regras_fiscais/taxes_calc.py
br_regras_fiscais-0.2.0.dist-info/LICENSE
br_regras_fiscais-0.2.0.dist-info/METADATA
br_regras_fiscais-0.2.0.dist-info/WHEEL
br_regras_fiscais-0.2.0.dist-info/RECORD
