Metadata-Version: 2.3
Name: br-regras-fiscais
Version: 0.2.0
Summary: Calculate BR taxes from NF total value, and calculate the original value of a NF from a received payment
License: MIT
Author: Bjorn Boschman
Author-email: bjorn.boschman@admdoctor.com.br
Requires-Python: >=3.9,<4.0
Classifier: License :: OSI Approved :: MIT License
Classifier: Programming Language :: Python :: 3
Classifier: Programming Language :: Python :: 3.9
Classifier: Programming Language :: Python :: 3.10
Classifier: Programming Language :: Python :: 3.11
Classifier: Programming Language :: Python :: 3.12
Classifier: Programming Language :: Python :: 3.13
